{
    "itemStatus":"Inactive",
    "maturityLevel":"Moderate",
    "mesh":"100% Mesh",
    "usage":"unpacking",
    "itemTitle":"",
    "Product features": {
        "1": "Maitreya, LaraX, flat chest, PetiteX  LaraX Only",
        "2": "Legacy, Perky,petite, Perkypetite, V-Tech, VTech, Bombshell, Pinup",
        "3": "eBody Reborn + Reborn VTech",
        "4": "Original, Artwork, 3D, Unique, Creative, Authentic",
        "5": ""
    },
    "extendedDescription":"",
    "keywords":"",
    "category":"Apparel",
    "itemPrice": "269",
    "slurl":"",
    "revenueDistributions":""

}
  